fastapi_amis_admin_cli/__init__.py
fastapi_amis_admin_cli/main.py
fastapi_amis_admin_cli/App/cookiecutter.json
fastapi_amis_admin_cli/App/{{cookiecutter.slug}}/__init__.py
fastapi_amis_admin_cli/App/{{cookiecutter.slug}}/admin.py
fastapi_amis_admin_cli/App/{{cookiecutter.slug}}/apis.py
fastapi_amis_admin_cli/App/{{cookiecutter.slug}}/crud.py
fastapi_amis_admin_cli/App/{{cookiecutter.slug}}/events.py
fastapi_amis_admin_cli/App/{{cookiecutter.slug}}/jobs.py
fastapi_amis_admin_cli/App/{{cookiecutter.slug}}/models.py
fastapi_amis_admin_cli/App/{{cookiecutter.slug}}/schemas.py
fastapi_amis_admin_cli/App/{{cookiecutter.slug}}/tests.py
fastapi_amis_admin_cli/Project/cookiecutter.json
fastapi_amis_admin_cli/Project/{{cookiecutter.slug}}/README.md
fastapi_amis_admin_cli/Project/{{cookiecutter.slug}}/pyproject.toml
fastapi_amis_admin_cli/Project/{{cookiecutter.slug}}/backend/.env
fastapi_amis_admin_cli/Project/{{cookiecutter.slug}}/backend/main.py
fastapi_amis_admin_cli/Project/{{cookiecutter.slug}}/backend/apps/__init__.py
fastapi_amis_admin_cli/Project/{{cookiecutter.slug}}/backend/core/__init__.py
fastapi_amis_admin_cli/Project/{{cookiecutter.slug}}/backend/core/globals.py
fastapi_amis_admin_cli/Project/{{cookiecutter.slug}}/backend/core/settings.py
fastapi_amis_admin_cli/commands/__init__.py
fastapi_amis_admin_cli/commands/main.py
fastapi_amis_admin_cli/commands/project.py
fastapi_amis_admin_cli/commands/utils.py
fastapi_amis_admin_cli-0.2.1.dist-info/entry_points.txt
fastapi_amis_admin_cli-0.2.1.dist-info/LICENSE
fastapi_amis_admin_cli-0.2.1.dist-info/WHEEL
fastapi_amis_admin_cli-0.2.1.dist-info/METADATA
fastapi_amis_admin_cli-0.2.1.dist-info/RECORD
