Metadata-Version: 2.1
Name: fastapi_amis_admin_cli
Version: 0.2.1
Summary: FastAPI-Amis-Admin-Cli is an extended library for quickly building `FastAPI-Amis-Admin` projects.
Keywords: fastapi-amis-admin-cli,fastapi-amis-admin,fastapi-user-auth,fastapi-APScheduler
Author-email: Atomi <1456417373@qq.com>
Maintainer-email: Atomi <1456417373@qq.com>
Requires-Python: >=3.7
Classifier: Framework :: FastAPI
Classifier: Environment :: Web Environment
Classifier: Topic :: System :: Systems Administration
Classifier: License :: OSI Approved :: Apache Software License
Classifier: Operating System :: OS Independent
Classifier: Programming Language :: Python :: 3
Classifier: Programming Language :: Python :: 3.6
Classifier: Programming Language :: Python :: 3.7
Classifier: Programming Language :: Python :: 3.8
Classifier: Programming Language :: Python :: 3.9
Classifier: Programming Language :: Python :: 3.10
Requires-Dist: typer>=0.9.0
Requires-Dist: cookiecutter>=2.1.1
Requires-Dist: psutil>=5.9.5
Requires-Dist: pytest >=6.2.4,<7.0.0 ; extra == "test"
Project-URL: FastAPI-Amis-Admin, https://github.com/amisadmin/fastapi-amis-admin
Project-URL: Source, https://github.com/amisadmin/fastapi-amis-admin-cli
Provides-Extra: test
